astrosn/__init__.py
astrosn/filters.py
astrosn/interp.py
astrosn/photometry.py
astrosn/sites.py
astrosn/sn_data.py
astrosn/supernova.py
astrosn/utils.py
astrosn/vega.dat
astrosn/version.py
astrosn/bolo/__init__.py
astrosn/bolo/arnett.py
astrosn/bolo/bb_fit_bootstrap_multithreaded.py
astrosn/bolo/bololc.py
astrosn/ingest/__init__.py
astrosn/ingest/collators.py
astrosn/ingest/converters.py
astrosn/ingest/flows.py
astrosn/ingest/ingest.py
astrosn/ingest/readers.py
astrosn/ingest/utils.py
astrosn/ingest/ztf.py
astrosn/plotting/__init__.py
astrosn/plotting/colors.py
astrosn/plotting/plot_lc.py
astrosn/plotting/premade_plots.py
astrosn-0.1.1.dist-info/LICENSE.md
astrosn-0.1.1.dist-info/WHEEL
astrosn-0.1.1.dist-info/METADATA
astrosn-0.1.1.dist-info/RECORD
